{
  "project_info": {
    "project_number": "642445473435",
    "project_id": "foodrescue-34370",
    "storage_bucket": "foodrescue-34370.firebasestorage.app"
  },
  "client": [
    {
      "client_info": {
        "mobilesdk_app_id": "1:642445473435:android:dd96a1410292e24d89783e",
        "android_client_info": {
          "package_name": "com.foodRescue"
        }
      },
      "oauth_client": [],
      "api_key": [
        {
          "current_key": "AIzaSyB9wWrq0lTFm-pRN106t_Dp-FRzAP9pDb8"
        }
      ],
      "services": {
        "appinvite_service": {
          "other_platform_oauth_client": []
        }
      }
    }
  ],
  "configuration_version": "1"
}